pbu/__init__.py
pbu/app_config.py
pbu/basic_monitor.py
pbu/constant_listing.py
pbu/datascience_util.py
pbu/date_time.py
pbu/debug_object.py
pbu/default_options.py
pbu/files.py
pbu/json.py
pbu/json_document.py
pbu/json_wrapper.py
pbu/logger.py
pbu/mongo_store.py
pbu/mysql_connection.py
pbu/mysql_store.py
pbu/paging.py
pbu/performance_logger.py
pbu/time_series.py
pbu-1.1.17.dist-info/LICENSE
pbu-1.1.17.dist-info/METADATA
pbu-1.1.17.dist-info/WHEEL
pbu-1.1.17.dist-info/top_level.txt
pbu-1.1.17.dist-info/RECORD
