Metadata-Version: 2.1
Name: pbu
Version: 1.1.17
Summary: Basic Utility module for the Python programming language
Home-page: https://github.com/ilfrich/python-basic-utils
Author: Peter Ilfrich
Author-email: das-peter@gmx.de
License: Apache-2.0
License-File: LICENSE
Requires-Dist: pytz
Requires-Dist: requests
Requires-Dist: pandas
Requires-Dist: python-dotenv
